<?xml version="1.0"?>
<StockFilteredStrategyBase xmlns:xsd="http://www.w3.org/2001/XMLSchema" xmlns:xsi="http://www.w3.org/2001/XMLSchema-instance">
  <Name>DONCHIAN_STOKS</Name>
  <TriggerName>STOKS(14,3,3)</TriggerName>
  <FilterName>DONCHIAN(80)</FilterName>
  <BuyTriggerEventName>BullishCrossing</BuyTriggerEventName>
  <ShortTriggerEventName>BearishCrossing</ShortTriggerEventName>
  <OkToBuyFilterEventName>CloseAboveMidLine</OkToBuyFilterEventName>
  <OkToShortFilterEventName>CloseBelowMidLine</OkToShortFilterEventName>
</StockFilteredStrategyBase>