<?xml version="1.0"?>
<ArrayOfStockWatchList xmlns:xsd="http://www.w3.org/2001/XMLSchema" xmlns:xsi="http://www.w3.org/2001/XMLSchema-instance">
  <StockWatchList>
    <Name>_LongTerm</Name>
    <StockList>
      <string>ALBIOMA</string>
      <string>ALTAMIR</string>
      <string>BIO UV GROUP</string>
      <string>DIAGEO</string>
      <string>MEDIAN TECHNOLOGIES</string>
      <string>MINT</string>
      <string>NOXXON</string>
      <string>PHARMASIMPLE</string>
      <string>RUBIS</string>
      <string>SOLUTIONS 30</string>
      <string>VALBIOTIS</string>
    </StockList>
  </StockWatchList>
  <StockWatchList>
    <Name>Abadie</Name>
    <StockList>
      <string>AKWEL</string>
      <string>CBO TERRITORIA</string>
      <string>CGG</string>
      <string>COFIDUR</string>
      <string>ENVEA</string>
      <string>GEVELOT</string>
      <string>GRAINES VOLTZ</string>
      <string>IDI</string>
      <string>MAUREL ET PROM</string>
      <string>NATIXIS</string>
      <string>PASSAT</string>
      <string>PLAST. VAL DE LOIRE</string>
      <string>SCBSM</string>
      <string>SERGEFERRARI GROUP</string>
      <string>SIGNAUX GIROD</string>
      <string>SMTPC</string>
      <string>SOGECLAIR</string>
      <string>U10 CORP.</string>
      <string>WE.CONNECT</string>
    </StockList>
  </StockWatchList>
  <StockWatchList>
    <Name>Alert</Name>
    <StockList>
      <string>FUT_BOND_EURO</string>
      <string>FUT_BOND_OAT</string>
      <string>FUT_BOND_US</string>
      <string>FUT_COM_COCOA</string>
      <string>FUT_COM_COFFEE</string>
      <string>FUT_COM_GOLD</string>
      <string>FUT_COM_NATURAL_GAS</string>
      <string>FUT_COM_OIL_CRUDE</string>
      <string>FUT_COM_PALLADIUM</string>
      <string>FUT_COM_PLATINUM</string>
      <string>FUT_COM_SILVER</string>
      <string>FUT_FX_EURGBP</string>
      <string>FUT_FX_EURUSD</string>
      <string>FUT_FX_USDJPY</string>
      <string>FUT_IND_CAC40</string>
      <string>FUT_IND_SP500</string>
      <string>FUT_IND_VIX</string>
      <string>INT_ACCOR</string>
      <string>INT_AIR FRANCE - KLM</string>
      <string>INT_BNP PARIBAS</string>
      <string>INT_CGG</string>
      <string>INT_CREDIT AGRICOLE</string>
      <string>INT_DERICHEBOURG</string>
      <string>INT_EDF</string>
      <string>INT_ENGIE</string>
      <string>INT_ERAMET</string>
      <string>INT_ILIAD</string>
      <string>INT_INGENICO GROUP</string>
      <string>INT_INNATE PHARMA</string>
      <string>INT_LVC</string>
      <string>INT_RENAULT</string>
      <string>INT_SOCIETE GENERALE</string>
      <string>INT_SOLOCAL</string>
      <string>INT_TOTAL</string>
      <string>INT_US_TESLA</string>
      <string>INT_VALEO</string>
      <string>INT_VALLOUREC</string>
    </StockList>
  </StockWatchList>
  <StockWatchList>
    <Name>Bank</Name>
    <StockList>
      <string>INT_BNP PARIBAS</string>
      <string>INT_CREDIT AGRICOLE</string>
      <string>INT_NATIXIS</string>
      <string>INT_SOCIETE GENERALE</string>
    </StockList>
  </StockWatchList>
  <StockWatchList>
    <Name>FollowUp</Name>
    <StockList>
      <string>ABIVAX</string>
      <string>ADOCIA</string>
      <string>AMOEBA BIOCIDE</string>
      <string>ARGAN</string>
      <string>ERYTECH PHARMA</string>
      <string>INNATE PHARMA</string>
      <string>INTEGRAGEN</string>
      <string>MERSEN</string>
      <string>MINT</string>
      <string>POXEL</string>
      <string>SPINEWAY</string>
    </StockList>
  </StockWatchList>
  <StockWatchList>
    <Name>RENAN</Name>
    <StockList>
      <string>ACTIA GROUP</string>
      <string>ADOCIA</string>
      <string>AGROGENERATION</string>
      <string>ALBIOMA</string>
      <string>ATARI</string>
      <string>ATEME</string>
      <string>BELIER</string>
      <string>BILENDI</string>
      <string>CHARGEURS</string>
      <string>DBV TECHNOLOGIES</string>
      <string>DERICHEBOURG</string>
      <string>EO2</string>
      <string>FIGEAC AERO</string>
      <string>GENSIGHT BIOLOGICS</string>
      <string>GROUPE OPEN</string>
      <string>INNATE PHARMA</string>
      <string>JACQUES BOGART</string>
      <string>JACQUET METALS</string>
      <string>MAISONS DU MONDE</string>
      <string>MAUNA KEA</string>
      <string>MOULINVEST</string>
      <string>NANOBIOTIX</string>
      <string>NEXANS</string>
      <string>NICOX</string>
      <string>ONCODESIGN</string>
      <string>PHARMASIMPLE</string>
      <string>SHOWROOMPRIVE</string>
      <string>SPIE</string>
      <string>TECHNICOLOR</string>
      <string>THERACLION</string>
    </StockList>
  </StockWatchList>
  <StockWatchList>
    <Name>SMALLCAPS</Name>
    <StockList>
      <string>BILENDI</string>
      <string>CATANA GROUP</string>
      <string>CBO TERRITORIA</string>
      <string>CIS (CATERING INTL SCES)</string>
      <string>CLASQUIN</string>
      <string>DLSI</string>
      <string>HIGH CO</string>
      <string>LUMIBIRD</string>
      <string>MGI DIGITAL GRAPHIC</string>
      <string>MICROWAVE VISION</string>
    </StockList>
  </StockWatchList>
</ArrayOfStockWatchList>